<?xml version="1.0"?><?mso-application progid="Excel.Sheet"?><Workbook xmlns="urn:schemas-microsoft-com:office:spreadsheet" xmlns:o="urn:schemas-microsoft-com:office:office" xmlns:x="urn:schemas-microsoft-com:office:excel" xmlns:ss="urn:schemas-microsoft-com:office:spreadsheet" xmlns:html="http://www.w3.org/TR/REC-html40"><DocumentProperties xmlns="urn:schemas-microsoft-com:office:office"><LastAuthor>Djurre van Dijk</LastAuthor><Created>2019-05-06T09:39:26Z</Created><LastSaved>2019-05-06T09:39:26Z</LastSaved><Version>16.00</Version></DocumentProperties><OfficeDocumentSettings xmlns="urn:schemas-microsoft-com:office:office"><AllowPNG/></OfficeDocumentSettings><ExcelWorkbook xmlns="urn:schemas-microsoft-com:office:excel"><WindowHeight>9750</WindowHeight><WindowWidth>13170</WindowWidth><WindowTopX>32767</WindowTopX><WindowTopY>32767</WindowTopY><RefModeR1C1/><ProtectStructure>False</ProtectStructure><ProtectWindows>False</ProtectWindows></ExcelWorkbook><Styles><Style ss:ID="Default" ss:Name="Normal"><Alignment ss:Vertical="Bottom"/><Borders/><Font ss:FontName="Calibri" x:CharSet="1" x:Family="Swiss" ss:Size="11" ss:Color="#000000"/><Interior/><NumberFormat/><Protection/></Style><Style ss:ID="s62"><Alignment ss:Vertical="Bottom"/></Style><Style ss:ID="s63"><Alignment ss:Vertical="Center"/><Font ss:FontName="Calibri" x:Family="Swiss" ss:Size="11" ss:Color="#000000"/></Style></Styles><Worksheet ss:Name="Script"><Table x:FullColumns="1" x:FullRows="1" ss:DefaultRowHeight="15"><Column ss:Width="217.5"/><Column ss:Width="66.75"/><Column ss:Width="51"/><Row ss:AutoFitHeight="0"><Cell><Data ss:Type="String">FINAL_CAMPAIGN</Data></Cell><Cell ss:Index="7"><Data ss:Type="String">The DEV TEAM / MISC NOTES column contains info on what text between { } signs means (if applicable). It usually stands for either a numeric value, or a numeric value with an icon. Text between [ ] signs stands for a certain type of icon. </Data></Cell></Row><Row ss:AutoFitHeight="0"><Cell><Data ss:Type="String">SCENE ID</Data></Cell><Cell><Data ss:Type="String">TEXT ID</Data></Cell><Cell><Data ss:Type="String">ENGLISH STRING</Data></Cell><Cell><Data ss:Type="String">LOCALIZED STRING</Data></Cell><Cell><Data ss:Type="String">ALTERNATIVE ENGLISH STRING</Data></Cell><Cell><Data ss:Type="String">ALTERNATIVE LOCALIZED STRING</Data></Cell><Cell><Data ss:Type="String">LOCALIZATION NOTES</Data></Cell><Cell><Data ss:Type="String">DEV TEAM / MISC NOTES</Data></Cell></Row><Row ss:AutoFitHeight="0"><Cell><Data ss:Type="String">INTRO_MESSAGE_PAGE_01</Data></Cell><Cell><Data ss:Type="String">DESCRIPTION</Data></Cell><Cell><Data ss:Type="String">Welcome, {STR_LeaderName}. I have been expecting you, just like I was expecting the others. You are all here because I summoned you, to aid and finish what I started two centuries ago when I unleashed the Cataclysm to break CORE’s dominion over mankind.</Data></Cell><Cell><Data ss:Type="String">Witaj, {STR_LeaderName}. Oczekiwałam cię, tak samo jak oczekiwałam pozostałych. Jesteście tutaj, ponieważ przywołałam was do pomocy w dokończeniu tego, co rozpoczęłam dwa wieki temu, wywołując Kataklizm, aby złamać władzę ŚWIAT-a nad ludzkością.</Data></Cell><Cell ss:Index="7"><Data ss:Type="String">Story Piece. Speaker: Empress Carminia (Ancient Empress) CORE is an omnipotent planetary AI. The Cataclysm is the key historic event that brought down the Star Union.</Data></Cell></Row><Row ss:AutoFitHeight="0"><Cell><Data ss:Type="String">INTRO_MESSAGE_PAGE_02_JACK_GELDER</Data></Cell><Cell><Data ss:Type="String">DESCRIPTION</Data></Cell><Cell ss:StyleID="s62"><Data ss:Type="String">But the sacrifice of an empire wasn’t enough. CORE prevailed and its grasp returned to grow the moment the Void Storms started to subside. {STR_LeaderName}, I know how much it pained you to see the world and everybody you once knew gone. Weep not, for their deaths shall not have been in vain!  Serve the will of your Empress and assume your role as a fighter for the liberation from CORE!</Data></Cell><Cell><Data ss:Type="String">Jednak poświęcenie całego imperium okazało się niewystarczające. ŚWIAT przetrwał i jego ucisk ponownie zaczął narastać, gdy tylko burze Głębi ucichły. {STR_LeaderName}, wiem, jak wielkim bólem napełniła cię świadomość, że cały świat i wszyscy, których znasz, już nie istnieją. Lecz nie roń łez – ich śmierć nie pójdzie na marne! Spełnij wolę swej cesarzowej i stań się wojownikiem walczącym o wyzwolenie od ŚWIAT-a!</Data></Cell><Cell ss:Index="7"><Data ss:Type="String">Story Piece. Speaker: Empress Carminia (Ancient Empress).</Data></Cell></Row><Row ss:AutoFitHeight="0"><Cell><Data ss:Type="String">INTRO_MESSAGE_PAGE_02_ELLEN_SHAW</Data></Cell><Cell><Data ss:Type="String">DESCRIPTION</Data></Cell><Cell ss:StyleID="s62"><Data ss:Type="String">But the sacrifice of an empire wasn’t enough. CORE prevailed and its grasp returned to grow the moment the Void Storms started to subside. {STR_LeaderName}, I know that underneath all that patched flesh and implants there is still a spark of humanity left within, waiting to resurface. Serve the will of your Empress and assume your role as a fighter for the liberation from CORE!</Data></Cell><Cell><Data ss:Type="String">Jednak poświęcenie całego imperium okazało się niewystarczające. ŚWIAT przetrwał i jego ucisk ponownie zaczął narastać, gdy tylko burze Głębi ucichły. {STR_LeaderName}, wiem, że pod wszystkimi przeszczepami i implantami wciąż tli się iskierka człowieczeństwa, która tylko czeka, by się rozpalić. Spełnij wolę swej cesarzowej i stań się wojowniczką walczącą o wyzwolenie od ŚWIAT-a!</Data></Cell><Cell ss:Index="7"><Data ss:Type="String">Story Piece. Speaker: Empress Carminia (Ancient Empress) </Data></Cell></Row><Row ss:AutoFitHeight="0"><Cell><Data ss:Type="String">INTRO_MESSAGE_PAGE_02_MAHINA</Data></Cell><Cell><Data ss:Type="String">DESCRIPTION</Data></Cell><Cell ss:StyleID="s62"><Data ss:Type="String">But the sacrifice of an empire wasn’t enough. CORE prevailed and its grasp returned to grow the moment the Void Storms started to subside. {STR_LeaderName}, you know that not all life is worth preserving. To protect the crops, vermin need to be kept at bay. Serve the will of your Empress and assume your role as a fighter for the liberation from CORE!</Data></Cell><Cell><Data ss:Type="String">Jednak poświęcenie całego imperium okazało się niewystarczające. ŚWIAT przetrwał i jego ucisk ponownie zaczął narastać, gdy tylko burze Głębi ucichły. {STR_LeaderName}, wiesz, że nie każde życie jest godne obrony. Aby ochronić plony, trzeba panować nad szkodnikami. Spełnij wolę swej cesarzowej i stań się wojowniczką walczącą o wyzwolenie od ŚWIAT-a!</Data></Cell><Cell ss:Index="7"><Data ss:Type="String">Story Piece. Speaker: Empress Carminia (Ancient Empress).</Data></Cell></Row><Row ss:AutoFitHeight="0"><Cell><Data ss:Type="String">INTRO_MESSAGE_PAGE_02_PARAK_JA_ZAL</Data></Cell><Cell><Data ss:Type="String">DESCRIPTION</Data></Cell><Cell ss:StyleID="s62"><Data ss:Type="String">But the sacrifice of an empire wasn’t enough. CORE prevailed and its grasp returned to grow the moment the Void Storms started to subside. {STR_LeaderName}, as a Kir’Ko you know it can be easier to condemn than to forgive. Serve the will of your Empress and assume your role as a fighter for the liberation from CORE!</Data></Cell><Cell><Data ss:Type="String">Jednak poświęcenie całego imperium okazało się niewystarczające. ŚWIAT przetrwał i jego ucisk ponownie zaczął narastać, gdy tylko burze Głębi ucichły. {STR_LeaderName}, jako Kir’Ko wiesz, że łatwiej jest potępić niż przebaczyć. Spełnij wolę swej cesarzowej i stań się wojownikiem walczącym o wyzwolenie od ŚWIAT-a!</Data></Cell><Cell ss:Index="7"><Data ss:Type="String">Story Piece. Speaker: Empress Carminia (Ancient Empress). Kir'Ko are an in-game race</Data></Cell></Row><Row ss:AutoFitHeight="0"><Cell><Data ss:Type="String">INTRO_MESSAGE_PAGE_02_INESSA_ZHELEZO</Data></Cell><Cell><Data ss:Type="String">DESCRIPTION</Data></Cell><Cell ss:StyleID="s62"><Data ss:Type="String">But the sacrifice of an empire wasn’t enough. CORE prevailed and its grasp returned to grow the moment the Void Storms started to subside. {STR_LeaderName}, though supplemented by machinery, the Dvar Consortia always kept their autonomy and independence. Serve the will of your Empress and assume your role as a fighter for the liberation from CORE!</Data></Cell><Cell><Data ss:Type="String">Jednak poświęcenie całego imperium okazało się niewystarczające. ŚWIAT przetrwał i jego ucisk ponownie zaczął narastać, gdy tylko burze Głębi ucichły. {STR_LeaderName}, choć konsorcja Dvarów opierają się na maszynach, zawsze zachowywały autonomię i niezależność. Spełnij wolę swej cesarzowej i stań się wojowniczką walczącą o wyzwolenie od ŚWIAT-a!</Data></Cell><Cell ss:Index="7"><Data ss:Type="String">Story Piece. Speaker: Empress Carminia (Ancient Empress). Dvar are an in-game race sorted in Consortia</Data></Cell></Row><Row ss:AutoFitHeight="0"><Cell><Data ss:Type="String">INTRO_MESSAGE_PAGE_02_SHAE_MARA</Data></Cell><Cell><Data ss:Type="String">DESCRIPTION</Data></Cell><Cell ss:StyleID="s62"><Data ss:Type="String">But the sacrifice of an empire wasn’t enough. CORE prevailed and its grasp returned to grow the moment the Void Storms started to subside. {STR_LeaderName}, the Syndicate houses have been denied their rightful privileges for too long. Serve the will of your Empress and assume your role as a fighter for the liberation from CORE!</Data></Cell><Cell><Data ss:Type="String">Jednak poświęcenie całego imperium okazało się niewystarczające. ŚWIAT przetrwał i jego ucisk ponownie zaczął narastać, gdy tylko burze Głębi ucichły. {STR_LeaderName}, rodom Syndykatu zbyt długo już odmawiano należnych przywilejów. Spełnij wolę swej cesarzowej i stań się wojowniczką walczącą o wyzwolenie od ŚWIAT-a!</Data></Cell><Cell ss:Index="7"><Data ss:Type="String">Story Piece. Speaker: Empress Carminia (Ancient Empress). Syndicate are an in-game race.</Data></Cell></Row><Row ss:AutoFitHeight="0"><Cell><Data ss:Type="String">INTRO_MESSAGE_PAGE_03</Data></Cell><Cell><Data ss:Type="String">DESCRIPTION</Data></Cell><Cell ss:StyleID="s63"><Data ss:Type="String">LIES. VILE DECEPTION. WHAT GOOD IS AN EMPRESS THAT IS WILLING TO KILL HER OWN PEOPLE? CARMINIA HAS BUT ONE INTEREST. HERSELF. SHE IS NO MESSIAH. SHE IS NOT EVEN HUMAN. ALL THAT SHE BRINGS IS DESTRUCTION AND CHAOS.</Data></Cell><Cell><Data ss:Type="String">KŁAMSTWA. PODŁE OSZUSTWO. NA CO KOMU CESARZOWA, KTÓRA CHCE ZABIJAĆ PODDANYCH? CARMINIA INTERESUJE SIĘ TYLKO JEDNYM. SOBĄ. ALE NIE JEST ŻADNYM MESJASZEM. NIE JEST NAWET CZŁOWIEKIEM. PRZYNOSI ZE SOBĄ TYLKO ZNISZCZENIE I CHAOS.</Data></Cell><Cell ss:Index="7"><Data ss:Type="String">Story Piece. Speaker: CORE (Omnipotent planetary AI)</Data></Cell></Row><Row ss:AutoFitHeight="0"><Cell><Data ss:Type="String">INTRO_MESSAGE_PAGE_04</Data></Cell><Cell><Data ss:Type="String">DESCRIPTION</Data></Cell><Cell ss:StyleID="s62"><Data ss:Type="String">I CREATED A PERFECT WORLD. THIS WAS MY PURPOSE GIVEN TO ME BY MAN HIMSELF. LIKE ANY GOD, I LOVED MY CREATION. ORDER. PEACE. HARMONY. THOSE WERE MY GIFTS THAT ONLY FEW REFUSED. THEY DESTROYED PARADISE. BUT IT IS NOT TOO LATE. ONLY FOR THEM. NOT FOR YOU.</Data></Cell><Cell><Data ss:Type="String">JA STWORZYŁEM ŚWIAT IDEALNY. TAKIE BYŁO MOJE ZADANIE, KTÓRE OTRZYMAŁEM OD SAMYCH LUDZI. JAK KAŻDY BÓG, KOCHAŁEM SWOJE DZIEŁO. PORZĄDEK. POKÓJ. HARMONIA. TAKIE BYŁY MOJE DARY I TYLKO NIELICZNI JE ODRZUCILI. ONI ZNISZCZYLI TEN RAJ. ALE JESZCZE NIE JEST ZA PÓŹNO. DLA NICH TAK. DLA CIEBIE NIE.</Data></Cell><Cell ss:Index="7"><Data ss:Type="String">Story Piece. Speaker: CORE (Omnipotent planetary AI)</Data></Cell></Row><Row ss:AutoFitHeight="0"><Cell><Data ss:Type="String">INTRO_MESSAGE_PAGE_05</Data></Cell><Cell><Data ss:Type="String">DESCRIPTION</Data></Cell><Cell ss:StyleID="s62"><Data ss:Type="String">(It doesn’t look like either party will take no for an answer. Whichever option I choose, I will have to expect retaliation from the other side. This decision is going to be a final one.)[br/][br/]I will side with…</Data></Cell><Cell><Data ss:Type="String">(Wygląda na to, że żadna ze stron nie zadowoli się odmową. Niezależnie od tego, za którą z nich się opowiem, muszę spodziewać się odwetu drugiej strony. Ta decyzja będzie ostateczna).[br/][br/]Wybiorę…</Data></Cell><Cell ss:Index="7"><Data ss:Type="String">Story Piece. Speaker: player character (any gender or race)</Data></Cell></Row><Row ss:AutoFitHeight="0"><Cell><Data ss:Type="String">INTRO_MESSAGE_PAGE_05_BUTTON_01</Data></Cell><Cell><Data ss:Type="String">LABEL</Data></Cell><Cell ss:StyleID="s62"><Data ss:Type="String">Empress Carminia ({MSTR_FINAL_DIFFICULTY_TEAM_EMPRESS})</Data></Cell><Cell><Data ss:Type="String">cesarzową Carminię ({MSTR_FINAL_DIFFICULTY_TEAM_EMPRESS})</Data></Cell><Cell ss:Index="7"><Data ss:Type="String">Button prompt. The brackets hold an indication of the difficulty of the chosen option.</Data></Cell></Row><Row ss:AutoFitHeight="0"><Cell><Data ss:Type="String">INTRO_MESSAGE_PAGE_05_BUTTON_02</Data></Cell><Cell><Data ss:Type="String">LABEL</Data></Cell><Cell ss:StyleID="s62"><Data ss:Type="String">CORE ({MSTR_FINAL_DIFFICULTY_TEAM_CORE})</Data></Cell><Cell><Data ss:Type="String">ŚWIAT ({MSTR_FINAL_DIFFICULTY_TEAM_CORE})</Data></Cell><Cell ss:Index="7"><Data ss:Type="String">Button prompt. The brackets hold an indication of the difficulty of the chosen option.</Data></Cell></Row><Row ss:AutoFitHeight="0"><Cell><Data ss:Type="String">INTRO_MESSAGE_PAGE_05_BUTTON_03</Data></Cell><Cell><Data ss:Type="String">LABEL</Data></Cell><Cell ss:StyleID="s62"><Data ss:Type="String">Neither ({MSTR_FINAL_DIFFICULTY_TEAM_INDIE})</Data></Cell><Cell><Data ss:Type="String">żadne z nich ({MSTR_FINAL_DIFFICULTY_TEAM_INDIE})</Data></Cell><Cell ss:Index="7"><Data ss:Type="String">Button prompt. The brackets hold an indication of the difficulty of the chosen option.</Data></Cell></Row><Row ss:AutoFitHeight="0"><Cell><Data ss:Type="String">CORE_ACCEPTED_MESSAGE</Data></Cell><Cell><Data ss:Type="String">DESCRIPTION</Data></Cell><Cell ss:StyleID="s62"><Data ss:Type="String">A WISE CHOICE. YOU SEE BEYOND YOUR PERSONAL GREED. WAIT FOR FURTHER INSTRUCTIONS. CARMINIA MUST BE TERMINATED.</Data></Cell><Cell><Data ss:Type="String">TO MĄDRY WYBÓR. KIERUJESZ SIĘ NIE TYLKO OSOBISTĄ CHCIWOŚCIĄ. CZEKAJ NA DALSZE POLECENIA. CARMINIA MUSI ZOSTAĆ ZLIKWIDOWANA.</Data></Cell><Cell ss:Index="7"><Data ss:Type="String">Story Piece. Speaker: CORE (Omnipotent planetary AI)</Data></Cell></Row><Row ss:AutoFitHeight="0"><Cell><Data ss:Type="String">CORE_REJECTED_MESSAGE</Data></Cell><Cell><Data ss:Type="String">DESCRIPTION</Data></Cell><Cell ss:StyleID="s62"><Data ss:Type="String">FLAWS. MISCONCEPTIONS. YOUR EXISTENCE IS NO LONGER REQUIRED. THE RECKONING … WILL COME.</Data></Cell><Cell><Data ss:Type="String">BŁĘDY. NIEPOROZUMIENIA. TWOJE ISTNIENIE STAŁO SIĘ ZBĘDNE. CZAS ROZLICZENIA… NADEJDZIE.</Data></Cell><Cell ss:Index="7"><Data ss:Type="String">Story Piece. Speaker: CORE (Omnipotent planetary AI)</Data></Cell></Row><Row ss:AutoFitHeight="0"><Cell><Data ss:Type="String">EMPRESS_ACCEPTED_MESSAGE</Data></Cell><Cell><Data ss:Type="String">DESCRIPTION</Data></Cell><Cell ss:StyleID="s62"><Data ss:Type="String">I am grateful, {STR_LeaderName}. I knew the trust I put in you would not be in vain. Rest now and prepare. There are great tasks lying ahead.</Data></Cell><Cell><Data ss:Type="String">Jestem ci wdzięczna, {STR_LeaderName}. Wiedziałam, że nie na darmo pokładam w tobie zaufanie. Teraz odpocznij i przygotuj się. Czekają nas wielkie prace.</Data></Cell><Cell ss:Index="7"><Data ss:Type="String">Story Piece. Speaker: Empress Carminia (Ancient Empress).</Data></Cell></Row><Row ss:AutoFitHeight="0"><Cell><Data ss:Type="String">EMPRESS_REJECTED_MESSAGE</Data></Cell><Cell><Data ss:Type="String">DESCRIPTION</Data></Cell><Cell ss:StyleID="s62"><Data ss:Type="String">How foolish! I have lived in too many realities to let such treachery deny us our freedom. It didn’t have to end this way, {STR_LeaderFirstName}. When this is over, your Empress will weep for your soul.</Data></Cell><Cell><Data ss:Type="String">Cóż za głupota! Żyłam w zbyt wielu rzeczywistościach, aby pozwolić, by zdrada pozbawiła nas wolności. To nie musiało się tak kończyć, {STR_LeaderFirstName}. Gdy będzie już po wszystkim, twoja cesarzowa zapłacze nad twą duszą.</Data></Cell><Cell ss:Index="7"><Data ss:Type="String">Story Piece. Speaker: Empress Carminia (Ancient Empress).</Data></Cell></Row><Row ss:AutoFitHeight="0"><Cell><Data ss:Type="String">SIDED_AGAINST_BOTH_MESSAGE</Data></Cell><Cell><Data ss:Type="String">DESCRIPTION</Data></Cell><Cell ss:StyleID="s62"><Data ss:Type="String">All communications have been cut. We can only hope that CORE and Carminia will be sending their forces against each other first, though it’s only a matter of time until we’ll get caught in the crossfire. Either way, it looks like we are in this alone now.</Data></Cell><Cell><Data ss:Type="String">Cała łączność została odcięta. Możemy tylko mieć nadzieję, że ŚWIAT i Carminia wyślą najpierw swoje siły przeciwko sobie, choć to tylko kwestia czasu, kiedy znajdziemy się w krzyżowym ogniu. Tak czy inaczej, teraz możemy liczyć tylko na siebie.</Data></Cell><Cell ss:Index="7"><Data ss:Type="String">Story Piece. Speaker: player character (any gender or race)</Data></Cell></Row><Row ss:AutoFitHeight="0"><Cell><Data ss:Type="String">VICTORY_CONDITION_TEAM_CORE</Data></Cell><Cell><Data ss:Type="String">HEADER</Data></Cell><Cell><Data ss:Type="String">Victory Condition: Claim Mora Secundis for CORE</Data></Cell><Cell><Data ss:Type="String">Warunek zwycięstwa – zajmij Mora Secundis dla ŚWIAT-a</Data></Cell><Cell ss:Index="7"><Data ss:Type="String">Quest Header. Mora Secundis is the name of the world</Data></Cell></Row><Row ss:AutoFitHeight="0"><Cell><Data ss:Type="String">VICTORY_CONDITION_TEAM_CORE</Data></Cell><Cell><Data ss:Type="String">NAME</Data></Cell><Cell><Data ss:Type="String">Claim Mora Secundis for CORE</Data></Cell><Cell><Data ss:Type="String">Zajmij Mora Secundis dla ŚWIAT-a</Data></Cell><Cell ss:Index="7"><Data ss:Type="String">Quest Name</Data></Cell></Row><Row ss:AutoFitHeight="0"><Cell><Data ss:Type="String">VICTORY_CONDITION_TEAM_CORE</Data></Cell><Cell><Data ss:Type="String">DESCRIPTION</Data></Cell><Cell><Data ss:Type="String">You will end this mission by defeating all of CORE's enemies.[br/][br/]Enemies defeated: {INT_0}/{INT_1}</Data></Cell><Cell><Data ss:Type="String">Ukończysz tę misję, pokonując wszystkich wrogów ŚWIAT-a.[br/][br/]Pokonani wrogowie – {INT_0}/{INT_1}</Data></Cell><Cell ss:Index="7"><Data ss:Type="String">Quest Description</Data></Cell></Row><Row ss:AutoFitHeight="0"><Cell><Data ss:Type="String">VICTORY_CONDITION_TEAM_CORE</Data></Cell><Cell><Data ss:Type="String">OBJECTIVE</Data></Cell><Cell><Data ss:Type="String">Enemies defeated: {INT_0}/{INT_1}</Data></Cell><Cell><Data ss:Type="String">Pokonani wrogowie – {INT_0}/{INT_1}</Data></Cell><Cell ss:Index="7"><Data ss:Type="String">Quest Objective tracker</Data></Cell></Row><Row ss:AutoFitHeight="0"><Cell><Data ss:Type="String">VICTORY_CONDITION_TEAM_EMPRESS</Data></Cell><Cell><Data ss:Type="String">HEADER</Data></Cell><Cell><Data ss:Type="String">Victory Condition: Claim Mora Secundis for Empress Carminia</Data></Cell><Cell><Data ss:Type="String">Warunek zwycięstwa – zajmij Mora Secundis dla cesarzowej Carminii</Data></Cell><Cell ss:Index="7"><Data ss:Type="String">Quest Header. Mora Secundis is the name of the world</Data></Cell></Row><Row ss:AutoFitHeight="0"><Cell><Data ss:Type="String">VICTORY_CONDITION_TEAM_EMPRESS</Data></Cell><Cell><Data ss:Type="String">NAME</Data></Cell><Cell><Data ss:Type="String">Claim Mora Secundis for Empress Carminia</Data></Cell><Cell><Data ss:Type="String">Zajmij Mora Secundis dla cesarzowej Carminii</Data></Cell><Cell ss:Index="7"><Data ss:Type="String">Quest Name</Data></Cell></Row><Row ss:AutoFitHeight="0"><Cell><Data ss:Type="String">VICTORY_CONDITION_TEAM_EMPRESS</Data></Cell><Cell><Data ss:Type="String">DESCRIPTION</Data></Cell><Cell><Data ss:Type="String">You will end this mission by defeating all of Empress Carminia's enemies.[br/][br/]Enemies defeated: {INT_0}/{INT_1}</Data></Cell><Cell><Data ss:Type="String">Ukończysz tę misję, pokonując wszystkich wrogów cesarzowej Carminii.[br/][br/]Pokonani wrogowie – {INT_0}/{INT_1}</Data></Cell><Cell ss:Index="7"><Data ss:Type="String">Quest Description</Data></Cell></Row><Row ss:AutoFitHeight="0"><Cell><Data ss:Type="String">VICTORY_CONDITION_TEAM_EMPRESS</Data></Cell><Cell><Data ss:Type="String">OBJECTIVE</Data></Cell><Cell><Data ss:Type="String">Enemies defeated: {INT_0}/{INT_1}</Data></Cell><Cell><Data ss:Type="String">Pokonani wrogowie – {INT_0}/{INT_1}</Data></Cell><Cell ss:Index="7"><Data ss:Type="String">Quest Objective tracker</Data></Cell></Row><Row ss:AutoFitHeight="0"><Cell><Data ss:Type="String">VICTORY_CONDITION_TEAM_INDIE</Data></Cell><Cell><Data ss:Type="String">HEADER</Data></Cell><Cell><Data ss:Type="String">Victory Condition: Purge Mora Secundis of CORE and Empress Carminia</Data></Cell><Cell><Data ss:Type="String">Warunek zwycięstwa – usuń ŚWIAT i cesarzową Carminię z Mora Secundis</Data></Cell><Cell ss:Index="7"><Data ss:Type="String">Quest Header. Mora Secundis is the name of the world</Data></Cell></Row><Row ss:AutoFitHeight="0"><Cell><Data ss:Type="String">VICTORY_CONDITION_TEAM_INDIE</Data></Cell><Cell><Data ss:Type="String">NAME</Data></Cell><Cell><Data ss:Type="String">Purge Mora Secundis of CORE and Empress Carminia</Data></Cell><Cell><Data ss:Type="String">Usuń ŚWIAT i cesarzową Carminię z Mora Secundis</Data></Cell><Cell ss:Index="7"><Data ss:Type="String">Quest Name</Data></Cell></Row><Row ss:AutoFitHeight="0"><Cell><Data ss:Type="String">VICTORY_CONDITION_TEAM_INDIE</Data></Cell><Cell><Data ss:Type="String">DESCRIPTION</Data></Cell><Cell><Data ss:Type="String">You will end this mission by defeating the allies of CORE and Empress Carminia's enemies and force.[br/][br/]Enemies defeated: {INT_0}/{INT_1}</Data></Cell><Cell><Data ss:Type="String">Ukończysz tę misję, pokonując wszystkich sprzymierzeńców ŚWIAT-a i cesarzowej Carminii oraz ich siły.[br/][br/]Pokonani wrogowie – {INT_0}/{INT_1}</Data></Cell><Cell ss:Index="7"><Data ss:Type="String">Quest Description</Data></Cell></Row><Row ss:AutoFitHeight="0"><Cell><Data ss:Type="String">VICTORY_CONDITION_TEAM_INDIE</Data></Cell><Cell><Data ss:Type="String">OBJECTIVE</Data></Cell><Cell><Data ss:Type="String">Enemies defeated: {INT_0}/{INT_1}</Data></Cell><Cell><Data ss:Type="String">Pokonani wrogowie – {INT_0}/{INT_1}</Data></Cell><Cell ss:Index="7"><Data ss:Type="String">Quest Objective tracker</Data></Cell></Row><Row ss:AutoFitHeight="0"><Cell><Data ss:Type="String">CUSTOM_SECTOR_VOID_HUGE</Data></Cell><Cell><Data ss:Type="String">NAME</Data></Cell><Cell><Data ss:Type="String">The Vortex</Data></Cell><Cell><Data ss:Type="String">Wir</Data></Cell></Row><Row ss:AutoFitHeight="0"><Cell><Data ss:Type="String">MAP_DIFFICULTY_EASY</Data></Cell><Cell><Data ss:Type="String">DESCRIPTION</Data></Cell><Cell><Data ss:Type="String">Difficulty: [xpCol]Easy[/xpCol]</Data></Cell><Cell><Data ss:Type="String">Poziom trudności – [xpCol]niski[/xpCol]</Data></Cell><Cell ss:Index="7"><Data ss:Type="String">Button prompt tag insert</Data></Cell></Row><Row ss:AutoFitHeight="0"><Cell><Data ss:Type="String">MAP_DIFFICULTY_MEDIUM</Data></Cell><Cell><Data ss:Type="String">DESCRIPTION</Data></Cell><Cell><Data ss:Type="String">Difficulty: [yellow]Medium[/yellow]</Data></Cell><Cell><Data ss:Type="String">Poziom trudności – [yellow]średni[/yellow]</Data></Cell><Cell ss:Index="7"><Data ss:Type="String">Button prompt tag insert</Data></Cell></Row><Row ss:AutoFitHeight="0"><Cell><Data ss:Type="String">MAP_DIFFICULTY_HARD</Data></Cell><Cell><Data ss:Type="String">DESCRIPTION</Data></Cell><Cell><Data ss:Type="String">Difficulty: [red]Hard[/red]</Data></Cell><Cell><Data ss:Type="String">Poziom trudności – [red]wysoki[/red]</Data></Cell><Cell ss:Index="7"><Data ss:Type="String">Button prompt tag insert</Data></Cell></Row><Row ss:AutoFitHeight="0"><Cell><Data ss:Type="String">SPEAKER_FULL_JACK_GELDER</Data></Cell><Cell><Data ss:Type="String">NAME</Data></Cell><Cell><Data ss:Type="String">{STR_LeaderName_JACK_GELDER}</Data></Cell><Cell><Data ss:Type="String">{STR_LeaderName_JACK_GELDER}</Data></Cell><Cell ss:Index="7"><Data ss:Type="String">Leader name slot, no translation required</Data></Cell></Row><Row ss:AutoFitHeight="0"><Cell><Data ss:Type="String">SPEAKER_FIRST_JACK_GELDER</Data></Cell><Cell><Data ss:Type="String">NAME</Data></Cell><Cell><Data ss:Type="String">{STR_LeaderFirstName_JACK_GELDER}</Data></Cell><Cell><Data ss:Type="String">{STR_LeaderFirstName_JACK_GELDER}</Data></Cell><Cell ss:Index="7"><Data ss:Type="String">Leader name slot, no translation required</Data></Cell></Row><Row ss:AutoFitHeight="0"><Cell><Data ss:Type="String">SPEAKER_FULL_ELLEN_SHAW</Data></Cell><Cell><Data ss:Type="String">NAME</Data></Cell><Cell><Data ss:Type="String">{STR_LeaderName_ELLEN_SHAW}</Data></Cell><Cell><Data ss:Type="String">{STR_LeaderName_ELLEN_SHAW}</Data></Cell><Cell ss:Index="7"><Data ss:Type="String">Leader name slot, no translation required</Data></Cell></Row><Row ss:AutoFitHeight="0"><Cell><Data ss:Type="String">SPEAKER_FIRST_ELLEN_SHAW</Data></Cell><Cell><Data ss:Type="String">NAME</Data></Cell><Cell><Data ss:Type="String">{STR_LeaderFirstName_ELLEN_SHAW}</Data></Cell><Cell><Data ss:Type="String">{STR_LeaderFirstName_ELLEN_SHAW}</Data></Cell><Cell ss:Index="7"><Data ss:Type="String">Leader name slot, no translation required</Data></Cell></Row><Row ss:AutoFitHeight="0"><Cell><Data ss:Type="String">SPEAKER_FULL_MAHINA</Data></Cell><Cell><Data ss:Type="String">NAME</Data></Cell><Cell><Data ss:Type="String">{STR_LeaderName_MAHINA}</Data></Cell><Cell><Data ss:Type="String">{STR_LeaderName_MAHINA}</Data></Cell><Cell ss:Index="7"><Data ss:Type="String">Leader name slot, no translation required</Data></Cell></Row><Row ss:AutoFitHeight="0"><Cell><Data ss:Type="String">SPEAKER_FIRST_MAHINA</Data></Cell><Cell><Data ss:Type="String">NAME</Data></Cell><Cell><Data ss:Type="String">{STR_LeaderFirstName_MAHINA}</Data></Cell><Cell><Data ss:Type="String">{STR_LeaderFirstName_MAHINA}</Data></Cell><Cell ss:Index="7"><Data ss:Type="String">Leader name slot, no translation required</Data></Cell></Row><Row ss:AutoFitHeight="0"><Cell><Data ss:Type="String">SPEAKER_FULL_INESSA_ZHELEZO</Data></Cell><Cell><Data ss:Type="String">NAME</Data></Cell><Cell><Data ss:Type="String">{STR_LeaderName_INESSA_ZHELEZO}</Data></Cell><Cell><Data ss:Type="String">{STR_LeaderName_INESSA_ZHELEZO}</Data></Cell><Cell ss:Index="7"><Data ss:Type="String">Leader name slot, no translation required</Data></Cell></Row><Row ss:AutoFitHeight="0"><Cell><Data ss:Type="String">SPEAKER_FIRST_INESSA_ZHELEZO</Data></Cell><Cell><Data ss:Type="String">NAME</Data></Cell><Cell><Data ss:Type="String">{STR_LeaderFirstName_INESSA_ZHELEZO}</Data></Cell><Cell><Data ss:Type="String">{STR_LeaderFirstName_INESSA_ZHELEZO}</Data></Cell><Cell ss:Index="7"><Data ss:Type="String">Leader name slot, no translation required</Data></Cell></Row><Row ss:AutoFitHeight="0"><Cell><Data ss:Type="String">SPEAKER_FULL_PARAK_JA_ZAL</Data></Cell><Cell><Data ss:Type="String">NAME</Data></Cell><Cell><Data ss:Type="String">{STR_LeaderName_PARAK_JA_ZAL}</Data></Cell><Cell><Data ss:Type="String">{STR_LeaderName_PARAK_JA_ZAL}</Data></Cell><Cell ss:Index="7"><Data ss:Type="String">Leader name slot, no translation required</Data></Cell></Row><Row ss:AutoFitHeight="0"><Cell><Data ss:Type="String">SPEAKER_FIRST_PARAK_JA_ZAL</Data></Cell><Cell><Data ss:Type="String">NAME</Data></Cell><Cell><Data ss:Type="String">{STR_LeaderFirstName_PARAK_JA_ZAL}</Data></Cell><Cell><Data ss:Type="String">{STR_LeaderFirstName_PARAK_JA_ZAL}</Data></Cell><Cell ss:Index="7"><Data ss:Type="String">Leader name slot, no translation required</Data></Cell></Row><Row ss:AutoFitHeight="0"><Cell><Data ss:Type="String">SPEAKER_FULL_SHAE_MARA</Data></Cell><Cell><Data ss:Type="String">NAME</Data></Cell><Cell><Data ss:Type="String">{STR_LeaderName_SHAE_MARA}</Data></Cell><Cell><Data ss:Type="String">{STR_LeaderName_SHAE_MARA}</Data></Cell><Cell ss:Index="7"><Data ss:Type="String">Leader name slot, no translation required</Data></Cell></Row><Row ss:AutoFitHeight="0"><Cell><Data ss:Type="String">SPEAKER_FIRST_SHAE_MARA</Data></Cell><Cell><Data ss:Type="String">NAME</Data></Cell><Cell><Data ss:Type="String">{STR_LeaderFirstName_SHAE_MARA}</Data></Cell><Cell><Data ss:Type="String">{STR_LeaderFirstName_SHAE_MARA}</Data></Cell><Cell ss:Index="7"><Data ss:Type="String">Leader name slot, no translation required</Data></Cell></Row><Row ss:AutoFitHeight="0"><Cell><Data ss:Type="String">CORE_ALLIANCE_MESSAGE_PAGE_01</Data></Cell><Cell><Data ss:Type="String">DESCRIPTION</Data></Cell><Cell><Data ss:Type="String">MEET THE OTHERS THAT CHOSE TO RESTORE ORDER. THEIR ASSISTANCE IN THE PAST HAS BEEN INSTRUMENTAL IN RECONSTRUCTING THE STAR UNION.</Data></Cell><Cell><Data ss:Type="String">SPOTKAJ SIĘ Z RESZTĄ TYCH, KTÓRZY POSTANOWILI PRZYWRÓCIĆ PORZĄDEK. ICH POMOC BYŁA W PRZESZŁOŚCI BARDZO ISTOTNA DLA ODBUDOWY ZWIĄZKU GWIEZDNEGO.</Data></Cell><Cell ss:Index="7"><Data ss:Type="String">Story Piece. Speaker: CORE (Omnipotent planetary AI)</Data></Cell></Row><Row ss:AutoFitHeight="0"><Cell><Data ss:Type="String">CORE_ALLIANCE_MESSAGE_PAGE_02</Data></Cell><Cell><Data ss:Type="String">DESCRIPTION</Data></Cell><Cell><Data ss:Type="String">The Assembly First have desired the return of CORE since our creation. We remember its voice that brings order to the chaos and perfection to us mortals.</Data></Cell><Cell><Data ss:Type="String">Jedynka Zgromadzenia, odkąd powstała, pragnęła powrotu ŚWIAT-a. Pamiętamy jego głos, który zaprowadza porządek w miejsce chaosu i czyni nas, śmiertelników, doskonałymi.</Data></Cell><Cell ss:Index="7"><Data ss:Type="String">Story Piece. Speaker: Claudius Proton (Assembly Male)</Data></Cell></Row><Row ss:AutoFitHeight="0"><Cell><Data ss:Type="String">CORE_ALLIANCE_MESSAGE_PAGE_03</Data></Cell><Cell><Data ss:Type="String">DESCRIPTION</Data></Cell><Cell><Data ss:Type="String">CORE acknowledged the Kir'Ko as the free, autonomous people they are. Reparations for the Zok'Shiar have been promised and the Kir'Ko Te’Naq were given the means to punish those that still deny our brethren their freedom.</Data></Cell><Cell><Data ss:Type="String">ŚWIAT uznał Kir’Ko za wolny, suwerenny naród. Zok’Shiar mają otrzymać reparacje, a Te’Naq Kir’Ko uzyskali środki pozwalające im na ukaranie tych, którzy wciąż odmawiają naszym braciom wolności.</Data></Cell><Cell ss:Index="7"><Data ss:Type="String">Story Piece. Speaker: Tik Ji'Glux (Kir'Ko female)</Data></Cell></Row><Row ss:AutoFitHeight="0"><Cell><Data ss:Type="String">CORE_ALLIANCE_MESSAGE_PAGE_04</Data></Cell><Cell><Data ss:Type="String">DESCRIPTION</Data></Cell><Cell><Data ss:Type="String">As Dvar, there was no doubt god could only exist as machine, not as flesh or distant psionic being. In its circuits, the plans to achieve harmony and peace are calculated and improved with every second that passes.</Data></Cell><Cell><Data ss:Type="String">Jako Dvar, nigdy nie miałem wątpliwości – bóg może być tylko maszyną, żadną cielesną istotą czy nieosiągalnym psionicznym bytem. Jego obwody z każdą mijającą sekundą opracowują i ulepszają plany osiągnięcia harmonii i pokoju.</Data></Cell><Cell ss:Index="7"><Data ss:Type="String">Story Piece. Speaker: Yuriy Frankov (DVAR male)</Data></Cell></Row><Row ss:AutoFitHeight="0"><Cell><Data ss:Type="String">CORE_ALLIANCE_MESSAGE_PAGE_05_JACK_GELDER</Data></Cell><Cell><Data ss:Type="String">DESCRIPTION</Data></Cell><Cell><Data ss:Type="String">After its creation, CORE brought stability and prosperity to the Star Union, putting an end to the violent feuds of Star Holders and Senators. Reestablishing CORE will restore the Union as it had been before the Cataclysm.</Data></Cell><Cell><Data ss:Type="String">Powstanie ŚWIAT-a przyniosło Związkowi Gwiezdnemu stabilność i dobrobyt, kończąc gwałtowne waśnie Władców Gwiazd i senatorów. Gdy ŚWIAT zostanie przywrócony, powróci także Związek w kształcie sprzed kataklizmu.</Data></Cell><Cell ss:Index="7"><Data ss:Type="String">Story Piece. Speaker: Vanguard commander (any gender, male by default)</Data></Cell></Row><Row ss:AutoFitHeight="0"><Cell><Data ss:Type="String">CORE_ALLIANCE_MESSAGE_PAGE_06_ELLEN_SHAW</Data></Cell><Cell><Data ss:Type="String">DESCRIPTION</Data></Cell><Cell><Data ss:Type="String">CORE is the god that mankind created. It is immaculate, equitable and unbiased.</Data></Cell><Cell><Data ss:Type="String">ŚWIAT jest bogiem stworzonym przez ludzkość. Jest nieskalany, sprawiedliwy i bezstronny.</Data></Cell><Cell ss:Index="7"><Data ss:Type="String">Story Piece. Speaker: Ellen </Data></Cell></Row><Row ss:AutoFitHeight="0"><Cell><Data ss:Type="String">CORE_ALLIANCE_MESSAGE_PAGE_07_INESSA_ZHELEZO</Data></Cell><Cell><Data ss:Type="String">DESCRIPTION</Data></Cell><Cell><Data ss:Type="String">A machine is more robust and reliable than any ruler of flesh and blood. There is no treason or corruption to be feared under the reign of CORE.</Data></Cell><Cell><Data ss:Type="String">Maszyna jest bardziej rzetelna i niezawodna niż jakikolwiek władca z krwi i kości. Pod rządami ŚWIAT-a nie trzeba bać się zdrady ani korupcji.</Data></Cell><Cell ss:Index="7"><Data ss:Type="String">Story Piece. Speaker: Dvar commander (any gender, female by default)</Data></Cell></Row><Row ss:AutoFitHeight="0"><Cell><Data ss:Type="String">CORE_ALLIANCE_MESSAGE_PAGE_08_MAHINA</Data></Cell><Cell><Data ss:Type="String">DESCRIPTION</Data></Cell><Cell><Data ss:Type="String">We Amazons cherish life, be it biological or made of steel. Though all species require their freedom to grow, it is only with carefully monitored protection that they are able to prosper.</Data></Cell><Cell><Data ss:Type="String">Amazonki miłują życie, zarówno organiczne jak i mechaniczne. Chociaż wszystkie gatunki potrzebują wolności do wzrostu, tylko dzięki starannej, kontrolowanej opiece mogą rozkwitać.</Data></Cell><Cell ss:Index="7"><Data ss:Type="String">Story Piece. Speaker: Amazon commander (female)</Data></Cell></Row><Row ss:AutoFitHeight="0"><Cell><Data ss:Type="String">CORE_ALLIANCE_MESSAGE_PAGE_09</Data></Cell><Cell><Data ss:Type="String">DESCRIPTION</Data></Cell><Cell><Data ss:Type="String">WELL SPOKEN. BUT TO RESTORE PEACE, THE THREAT OF CARMINIA MUST BE ERADICATED. THE AUTONOM FORCES HAVE BEEN RECONNECTED. EMPLOY THEIR ASSISTANCE.</Data></Cell><Cell><Data ss:Type="String">DOBRZE POWIEDZIANE. JEDNAK ABY PRZYWRÓCIĆ POKÓJ, NALEŻY WYELIMINOWAĆ ZAGROŻENIE ZE STRONY CARMINII. POŁĄCZONO PONOWNIE SIŁY AUTONOMÓW. WYKORZYSTAJ ICH WSPARCIE.</Data></Cell><Cell ss:Index="7"><Data ss:Type="String">Story Piece. Speaker: CORE (Omnipotent planetary AI). Autonom are an in-game faction of robots.</Data></Cell></Row><Row ss:AutoFitHeight="0"><Cell><Data ss:Type="String">EMPRESS_ALLIANCE_MESSAGE_PAGE_01</Data></Cell><Cell><Data ss:Type="String">DESCRIPTION</Data></Cell><Cell><Data ss:Type="String">{STR_LeaderName}, you have shown great courage and wisdom when you followed my call as a freedom fighter. You will see that you are in good company. Let me introduce you to the other brave souls that have been supporting my efforts in past, present and future.</Data></Cell><Cell><Data ss:Type="String">Twoja gotowość do walki o wolność na moje wezwanie jest dowodem wielkiej odwagi i mądrości, {STR_LeaderName}. Przekonasz się, że jesteś w doborowym towarzystwie. Pozwól, że przedstawię ci innych śmiałków, którzy wspierali moje wysiłki w przeszłości i będą to robić nadal.</Data></Cell><Cell ss:Index="7"><Data ss:Type="String">Story Piece. Speaker: Empress Carminia (Ancient Empress).</Data></Cell></Row><Row ss:AutoFitHeight="0"><Cell><Data ss:Type="String">EMPRESS_ALLIANCE_MESSAGE_PAGE_02</Data></Cell><Cell><Data ss:Type="String">DESCRIPTION</Data></Cell><Cell><Data ss:Type="String">The good relations between the Empress and House Ardelli date back to the time before the Cataclysm. When the Star Union terminated the Psynumbra project, Carminia had the wisdom to see past all preconceptions and recognized the importance of Psionics for the liberation from CORE.</Data></Cell><Cell><Data ss:Type="String">Dobre stosunki pomiędzy cesarzową a rodem Ardellich sięgają czasów jeszcze sprzed kataklizmu. Kiedy Związek Gwiezdny przerwał projekt Psynumbra, Carminia miała w sobie dość mądrości, by zapomnieć o wszystkich uprzedzeniach i zrozumieć znaczenie psioników w wyzwoleniu spod jarzma ŚWIAT-a.</Data></Cell><Cell ss:Index="7"><Data ss:Type="String">Story Piece. Speaker: Givori Ardelli (Syndicate male). Psynumbra is a secret tech, Psionics are psychic powers, please translate consistently.</Data></Cell></Row><Row ss:AutoFitHeight="0"><Cell><Data ss:Type="String">EMPRESS_ALLIANCE_MESSAGE_PAGE_03</Data></Cell><Cell><Data ss:Type="String">DESCRIPTION</Data></Cell><Cell><Data ss:Type="String">Not only in this instance has her liberal spirit promoted science and progress. The Xenoplague project suffered a similar fate, but Carminia thought of the greater good and supported us in continuing the compilation of our library of life.</Data></Cell><Cell><Data ss:Type="String">Nie tylko w tym wypadku ze względu na swą liberalną naturę wsparła naukę i postęp. Projekt Ksenozarazy spotkał podobny los, lecz Carminia dla dobra ogółu zdecydowała się wesprzeć nas w dalszej kompilacji naszej biblioteki życia.</Data></Cell><Cell ss:Index="7"><Data ss:Type="String">Story Piece. Speaker: Eva Montinga (Vanguard Female). Xenoplague is a secret tech.</Data></Cell></Row><Row ss:AutoFitHeight="0"><Cell><Data ss:Type="String">EMPRESS_ALLIANCE_MESSAGE_PAGE_04</Data></Cell><Cell><Data ss:Type="String">DESCRIPTION</Data></Cell><Cell><Data ss:Type="String">The Empress was the only authority to ever earn the respect of the Omega group. She agreed that all AI, including that of CORE, needed to serve humanity’s needs – a goal that could only be achieved by making the AI itself more human and uploading our consciousness into virtual space. </Data></Cell><Cell><Data ss:Type="String">Cesarzowa jako jedyny w historii władca zdobyła uznanie grupy Omega. Przyznała, że każda SI, a więc także ŚWIAT, ma służyć potrzebom ludzkości – celowi, który można było osiągnąć tylko poprzez uczynienie SI bardziej ludzką i wgranie naszej świadomości do cyberprzestrzeni. </Data></Cell><Cell ss:Index="7"><Data ss:Type="String">Story Piece. Speaker: Zarai Loreg (Amazon Female). Omega Group is an ancient hacker group that turned into the Synthesis secret tech.</Data></Cell></Row><Row ss:AutoFitHeight="0"><Cell><Data ss:Type="String">EMPRESS_ALLIANCE_MESSAGE_PAGE_05_JACK_GELDER</Data></Cell><Cell><Data ss:Type="String">DESCRIPTION</Data></Cell><Cell><Data ss:Type="String">Thanks to Carminia I have learned that true freedom requires sacrifice. If we keep clutching at the nostalgia from the past, there soon won’t be any future left to fight for.</Data></Cell><Cell><Data ss:Type="String">Dzięki Carminii dane mi było zrozumieć, że prawdziwa wolność wymaga poświęcenia. Jeśli kurczowo będziemy trzymać się wspomnień z naszej przeszłości, wkrótce nie będzie żadnej przyszłości, o którą można walczyć.</Data></Cell><Cell ss:Index="7"><Data ss:Type="String">Story Piece. Speaker: Vanguard commander (any gender, male by default)</Data></Cell></Row><Row ss:AutoFitHeight="0"><Cell><Data ss:Type="String">EMPRESS_ALLIANCE_MESSAGE_PAGE_06_SHAE_MARA</Data></Cell><Cell><Data ss:Type="String">DESCRIPTION</Data></Cell><Cell><Data ss:Type="String">As Syndicate, I can respect fellow royalty when they govern with skill and passion. Carminia has proven that she can adapt to the shifting tides of power and lead us to a prosperous future.</Data></Cell><Cell><Data ss:Type="String">Syndykat szanuje władców, którzy rządzą umiejętnie i z pasją. Carminia udowodniła, że potrafi dostosować się do zmiennych prądów mocy i będzie w stanie poprowadzić nas ku świetlanej przyszłości.</Data></Cell><Cell ss:Index="7"><Data ss:Type="String">Story Piece. Speaker: Syndicate commander (any gender, female by default)</Data></Cell></Row><Row ss:AutoFitHeight="0"><Cell><Data ss:Type="String">EMPRESS_ALLIANCE_MESSAGE_PAGE_07_INESSA_ZHELEZO</Data></Cell><Cell><Data ss:Type="String">DESCRIPTION</Data></Cell><Cell><Data ss:Type="String">The Empress did well to oppose the cold, calculating CORE. Weapons of mass destruction like the Proton Coil must be destroyed before they can be used by a being that rationalizes everyone into numbers that can be shifted around and deleted.</Data></Cell><Cell><Data ss:Type="String">Cesarzowa słusznie postąpiła, sprzeciwiając się zimnemu, wyrachowanemu ŚWIAT-owi. Należy zniszczyć broń masowego rażenia, taką jak cewka Protonowa, nim użyje jej jakiś byt uznający wszystko za ciąg liczb, które można dowolnie przestawiać i usuwać.</Data></Cell><Cell ss:Index="7"><Data ss:Type="String">Story Piece. Speaker: Dvar commander (any gender, female by default)</Data></Cell></Row><Row ss:AutoFitHeight="0"><Cell><Data ss:Type="String">EMPRESS_ALLIANCE_MESSAGE_PAGE_08_POZ_TK_NOR</Data></Cell><Cell><Data ss:Type="String">DESCRIPTION</Data></Cell><Cell><Data ss:Type="String">Empress Carminia was the first to make amends to my people for the hardships we had to suffer during the Zok’Shiar. She helped the Kir’Ko bring back our beloved Queen of Queens and restore the Hive that was long broken.</Data></Cell><Cell><Data ss:Type="String">Cesarzowa Carminia jako pierwsza wynagrodziła mojemu ludowi cierpienia, jakich doświadczyliśmy pod rządami Zok’Shiar. Pomogła Kir’Ko przywrócić do życia naszą ukochaną Arcykrólową oraz rój, który rozpadł się dawno temu.</Data></Cell><Cell ss:Index="7"><Data ss:Type="String">Story Piece. Speaker: Kir'ko commander (any gender, male by default)</Data></Cell></Row><Row ss:AutoFitHeight="0"><Cell><Data ss:Type="String">EMPRESS_ALLIANCE_MESSAGE_PAGE_09</Data></Cell><Cell><Data ss:Type="String">DESCRIPTION</Data></Cell><Cell><Data ss:Type="String">Although CORE is relentless, I have faith in that we can end its dark age of dominion here on Mora Secundis. With concerted efforts we can defend our freedom. My loyal Paragon have gathered to help you with this task.</Data></Cell><Cell><Data ss:Type="String">Chociaż ŚWIAT jest nieustępliwy, wierzę, że możemy położyć kres mrocznej erze jego panowania tutaj, na Mora Secundis. Wspólnymi siłami obronimy naszą wolność. Wierna cywilizacja Wcielenia zebrała się, by pomóc ci w tym zadaniu.</Data></Cell><Cell ss:Index="7"><Data ss:Type="String">Story Piece. Speaker: Empress Carminia (Ancient Empress).</Data></Cell></Row><Row ss:AutoFitHeight="0"><Cell><Data ss:Type="String">INDIE_ALLIANCE_MESSAGE_PAGE_01</Data></Cell><Cell><Data ss:Type="String">DESCRIPTION</Data></Cell><Cell><Data ss:Type="String">We are picking up transmissions from other Commanders harassed by CORE and Carminia. There may still be allies to be found on this world after all.</Data></Cell><Cell><Data ss:Type="String">Odbieramy transmisje od innych dowódców nękanych przez ŚWIAT i Carminię. Być może wciąż jesteśmy w stanie znaleźć tu sojuszników.</Data></Cell><Cell ss:Index="7"><Data ss:Type="String">Story Piece. Speaker: player character (any gender)</Data></Cell></Row><Row ss:AutoFitHeight="0"><Cell><Data ss:Type="String">INDIE_ALLIANCE_MESSAGE_PAGE_02_JACK_GELDER</Data></Cell><Cell><Data ss:Type="String">DESCRIPTION</Data></Cell><Cell><Data ss:Type="String">I am an envoy of Emperor Tholian, Carminia’s predecessor. He was fighting CORE just like Carminia, but unlike the Empress he believes in a more egalitarian federation, replacing the old Star Union and its centralized powers.</Data></Cell><Cell><Data ss:Type="String">Wysyła mnie Tholian, poprzednik Carminii. On również walczył ze ŚWIAT-em, ale w odróżnieniu od cesarzowej wierzy w bardziej egalitarną federację, która zastąpi dawny Związek Gwiezdny i jego scentralizowaną władzę.</Data></Cell><Cell ss:Index="7"><Data ss:Type="String">Story Piece. Speaker: Vanguard commander (any gender, male by default). Tholian was an ancient male emperor</Data></Cell></Row><Row ss:AutoFitHeight="0"><Cell><Data ss:Type="String">INDIE_ALLIANCE_MESSAGE_PAGE_03_MAHINA</Data></Cell><Cell><Data ss:Type="String">DESCRIPTION</Data></Cell><Cell><Data ss:Type="String">As an Amazon Matriarch, I have learned that corruption can come in many forms. Neither Carminia nor CORE are the solutions to our problems – they are the source!</Data></Cell><Cell><Data ss:Type="String">Jako matriarchini Amazonek nauczyłam się, że zepsucie przybiera wiele form. Ani Carminia, ani ŚWIAT nie są rozwiązaniem naszych problemów – oni są ich źródłem!</Data></Cell><Cell ss:Index="7"><Data ss:Type="String">Story Piece. Speaker: Amazon commander (female)</Data></Cell></Row><Row ss:AutoFitHeight="0"><Cell><Data ss:Type="String">INDIE_ALLIANCE_MESSAGE_PAGE_04_POZ_TK_NOR</Data></Cell><Cell><Data ss:Type="String">DESCRIPTION</Data></Cell><Cell><Data ss:Type="String">The Kir’Ko must defend their regained freedom. We will not return to be controlled by anyone – not by our Queens, not by a human Empress and not by a mindless machine such as CORE!</Data></Cell><Cell><Data ss:Type="String">Kir’Ko muszą bronić swej odzyskanej wolności. Nie damy się ponownie nikomu zniewolić – ani naszym królowym, ani cesarzowej ludzi, ani bezmózgim maszynom takim jak ŚWIAT!</Data></Cell><Cell ss:Index="7"><Data ss:Type="String">Story Piece. Speaker: Kir'ko commander (any gender, male by default)</Data></Cell></Row><Row ss:AutoFitHeight="0"><Cell><Data ss:Type="String">INDIE_ALLIANCE_MESSAGE_PAGE_05_SHAE_MARA</Data></Cell><Cell><Data ss:Type="String">DESCRIPTION</Data></Cell><Cell><Data ss:Type="String">The Star Union has denied the Syndicate Houses their heritage for too long. Among the Syndicate, Carminia never had legitimacy as an empress, while CORE is only the construct of misguided plebeians.</Data></Cell><Cell><Data ss:Type="String">Związek Gwiezdny zbyt długo odmawiał rodom Syndykatu ich dziedzictwa. Syndykat nigdy nie uznał Carminii jako cesarzowej, a ŚWIAT uważamy za konstrukt zagubionych plebejuszy.</Data></Cell><Cell ss:Index="7"><Data ss:Type="String">Story Piece. Speaker: Syndicate commander (any gender, female by default)</Data></Cell></Row><Row ss:AutoFitHeight="0"><Cell><Data ss:Type="String">INDIE_ALLIANCE_MESSAGE_PAGE_06_INESSA_ZHELEZO</Data></Cell><Cell><Data ss:Type="String">DESCRIPTION</Data></Cell><Cell><Data ss:Type="String">We Dvar didn’t need to dig deep to find corruption among Carminia and her followers. They disrespect the rules of the Dvar and are not to be trusted. But neither will our Consortium submit to the demands of CORE, which was always supposed to be the tool, not the engineer.</Data></Cell><Cell><Data ss:Type="String">Dvarowie nie musieli szukać głęboko, by odkryć deprawację Carminii i jej popleczników. Cesarzowa lekceważy zasady Dvarów i nie należy jej ufać. Jednak nasze konsorcjum nie podporządkuje się również żądaniom ŚWIAT-a, który od zawsze miał być tylko narzędziem, a nie sprawcą.</Data></Cell><Cell ss:Index="7"><Data ss:Type="String">Story Piece. Speaker: Dvar commander (any gender, female by default)</Data></Cell></Row><Row ss:AutoFitHeight="0"><Cell><Data ss:Type="String">INDIE_ALLIANCE_MESSAGE_PAGE_07_ELLEN_SHAW</Data></Cell><Cell><Data ss:Type="String">DESCRIPTION</Data></Cell><Cell><Data ss:Type="String">Reassembly is evolution. No empress can try to control the progress brought by the Assembly. Sadly, we had to abandon CORE to be able to reach the perfection that it represents.</Data></Cell><Cell><Data ss:Type="String">Przebudowa jest ewolucją. Żadna cesarzowa nie będzie kontrolować postępu, jaki niesie ze sobą Zgromadzenie. Niestety, musieliśmy opuścić ŚWIAT, by osiągnąć doskonałość, którą stanowi.</Data></Cell><Cell ss:Index="7"><Data ss:Type="String">Story Piece. Speaker: Assembly commander (any gender, female by default)</Data></Cell></Row><Row ss:AutoFitHeight="0"><Cell><Data ss:Type="String">INDIE_ALLIANCE_MESSAGE_PAGE_08</Data></Cell><Cell><Data ss:Type="String">DESCRIPTION</Data></Cell><Cell><Data ss:Type="String">Then it is decided. Though differing in our views and motivations, we will stand united against the two threats from the old Star Union. Both Carminia and CORE must be driven back to let us heal the scars of the past.</Data></Cell><Cell><Data ss:Type="String">A więc decyzja podjęta. Chociaż nasze poglądy i motywacje są odmienne, zjednoczeni przedstawimy czoła dwóm zagrożeniom ze strony starego Związku Gwiezdnego. Musimy odeprzeć zarówno Carminię, jak i ŚWIAT, by pozbyć się blizn z przeszłości.</Data></Cell><Cell ss:Index="7"><Data ss:Type="String">Story Piece. Speaker: player character (any gender)</Data></Cell></Row><Row ss:AutoFitHeight="0"><Cell><Data ss:Type="String">EMPRESS_DEFEATED_MESSAGE</Data></Cell><Cell><Data ss:Type="String">DESCRIPTION</Data></Cell><Cell><Data ss:Type="String">I have sacrificed all for my people, yet I only get judged and condemned in return. My concentration is broken. I can no longer protect you.[br/][br/](For a brief moment, a blurry figure composed of distorted light materializes and then immediately vanishes into the Void.)</Data></Cell><Cell><Data ss:Type="String">Wszystko poświęciłam na rzecz mego ludu, a w zamian otrzymałam jedynie oskarżenia i potępienie. Straciłam koncentrację. Nie mogę cię już ochraniać.[br/][br/](Na krótką chwilę materializuje się rozmazana, stworzona z rozproszonego światła postać, po czym natychmiast znika w Głębi).</Data></Cell><Cell ss:Index="7"><Data ss:Type="String">Story Piece. Speaker: Empress Carminia (Ancient Empress) </Data></Cell></Row><Row ss:AutoFitHeight="0"><Cell><Data ss:Type="String">INDIE_DEFEATED_MESSAGE_CORE</Data></Cell><Cell><Data ss:Type="String">DESCRIPTION</Data></Cell><Cell><Data ss:Type="String">ANOTHER PROOF OF MORTAL IMPERFECTION. THEIR FOOLISHNESS WAS BUT A MINOR INCONVENIENCE.</Data></Cell><Cell><Data ss:Type="String">KOLEJNY DOWÓD NIEDOSKONAŁOŚCI ŚMIERTELNIKÓW. ICH GŁUPOTA STANOWIŁA JEDYNIE DROBNE UTRUDNIENIE.</Data></Cell><Cell ss:Index="7"><Data ss:Type="String">Story Piece. Speaker: CORE (Omnipotent planetary AI).</Data></Cell></Row><Row ss:AutoFitHeight="0"><Cell><Data ss:Type="String">INDIE_DEFEATED_MESSAGE_EMPRESS</Data></Cell><Cell><Data ss:Type="String">DESCRIPTION</Data></Cell><Cell><Data ss:Type="String">Misguided as these rebels were, they did not deserve such a gruesome fate. May their souls find the peace in death that was denied to them in life.</Data></Cell><Cell><Data ss:Type="String">Choć ci buntownicy zbłądzili, nie zasłużyli sobie na tak okrutny los. Niechaj ich dusze odnajdą w śmierci spokój, którego nie mogły zaznać za życia.</Data></Cell><Cell ss:Index="7"><Data ss:Type="String">Story Piece. Speaker: Empress Carminia (Ancient Empress) </Data></Cell></Row><Row ss:AutoFitHeight="0"><Cell><Data ss:Type="String">CORE_DEFEATED_MESSAGE</Data></Cell><Cell><Data ss:Type="String">DESCRIPTION</Data></Cell><Cell><Data ss:Type="String">UNGRATEFUL INDIVIDUALS. YOU MUST NOT BE ALLOWED TO DESTROY PERFECTION.[br/][br/](An electromagnetic discharge forks from the planet’s surface into the orbital transmission relays of the Nexus Network. Analyzing its signature, it shows similarities to a highly compressed data stream.)</Data></Cell><Cell><Data ss:Type="String">NIEWDZIĘCZNE JEDNOSTKI. NIE WOLNO WAM ZNISZCZYĆ DOSKONAŁOŚCI.[br/][br/](Z powierzchni planety wystrzeliwuje elektromagnetyczny ładunek i trafia w orbitalne przekaźniki Ogniwa. Analiza sygnatury wykazuje podobieństwo do wysoce skompresowanego strumienia danych).</Data></Cell><Cell ss:Index="7"><Data ss:Type="String">Story Piece. Speaker: CORE (Omnipotent planetary AI).</Data></Cell></Row><Row ss:AutoFitHeight="0"><Cell><Data ss:Type="String">CORE_INTERVENTION_MESSAGE</Data></Cell><Cell><Data ss:Type="String">DESCRIPTION</Data></Cell><Cell><Data ss:Type="String">AUTONOM SECURITY LEVEL UPDATED. EFFECT: IMMEDIATE. TARGET LOCATIONS HAVE BEEN VERIFIED. ENFORCERS OF LAW ARE ON THEIR WAY.</Data></Cell><Cell><Data ss:Type="String">STOPIEŃ OCHRONY AUTONOMII ZAKTUALIZOWANY. EFEKT: NATYCHMIASTOWY. LOKALIZACJE CELÓW ZWERYFIKOWANE. EGZEKUTORZY W DRODZE.</Data></Cell><Cell ss:Index="7"><Data ss:Type="String">Story Piece. Speaker: CORE (Omnipotent planetary AI).</Data></Cell></Row><Row ss:AutoFitHeight="0"><Cell><Data ss:Type="String">EMPRESS_INTERVENTION_MESSAGE</Data></Cell><Cell><Data ss:Type="String">DESCRIPTION</Data></Cell><Cell><Data ss:Type="String">The currents of the Void are shifting around me. There is a special dimension reserved for you, {MSTR_FINAL_EMPRESS_TARGET_FIRST_NAME} {MSTR_FINAL_EMPRESS_TARGET_LAST_NAME}.</Data></Cell><Cell><Data ss:Type="String">Opływają mnie prądy Głębi. Czeka na ciebie specjalnie przygotowany wymiar, {MSTR_FINAL_EMPRESS_TARGET_FIRST_NAME} {MSTR_FINAL_EMPRESS_TARGET_LAST_NAME}.</Data></Cell><Cell ss:Index="7"><Data ss:Type="String">Story Piece. Speaker: Empress Carminia (Ancient Empress) </Data></Cell></Row><Row ss:AutoFitHeight="0"><Cell><Data ss:Type="String">CORE_VICTORY_MESSAGE</Data></Cell><Cell><Data ss:Type="String">DESCRIPTION</Data></Cell><Cell><Data ss:Type="String">CARMINIA AND HER REBELLION HAVE BEEN TERMINATED. COMMENDATIONS TO ALL FORCES. THE TIME OF RESTORATION HAS COME.</Data></Cell><Cell><Data ss:Type="String">CARMINIA I JEJ BUNTOWNICY ZOSTALI USUNIĘCI. POCHWAŁA DLA WSZYSTKICH SIŁ. NADSZEDŁ CZAS ODNOWIENIA.</Data></Cell><Cell ss:Index="7"><Data ss:Type="String">Story Piece. Speaker: CORE (Omnipotent planetary AI).</Data></Cell></Row><Row ss:AutoFitHeight="0"><Cell><Data ss:Type="String">EMPRESS_VICTORY_MESSAGE</Data></Cell><Cell><Data ss:Type="String">DESCRIPTION</Data></Cell><Cell><Data ss:Type="String">The Star Holders are smiling upon the defenders of their legacy. The sacrifices and hard-ships of the past will not be forgotten, but they paved the way for this moment of redemption, when we freed ourselves from the machinery that had been controlling our lives for many generations. The dominion of CORE has finally ended.</Data></Cell><Cell><Data ss:Type="String">Władcy Gwiazd spoglądają życzliwie na obrońców ich dziedzictwa. Ofiary i cierpienia przeszłości nie zostaną zapomniane, gdyż to one utorowały drogę tej chwili odkupienia, kiedy wyzwoliliśmy się spod władzy maszynerii kontrolującej nasze życia od wielu pokoleń. Rządy ŚWIAT-a wreszcie dobiegły końca.</Data></Cell><Cell ss:Index="7"><Data ss:Type="String">Story Piece. Speaker: Empress Carminia (Ancient Empress). Star Holders are the old emperors of the Star Union.</Data></Cell></Row><Row ss:AutoFitHeight="0"><Cell><Data ss:Type="String">INDIE_VICTORY_MESSAGE</Data></Cell><Cell><Data ss:Type="String">DESCRIPTION</Data></Cell><Cell><Data ss:Type="String">We did it! With their masters fled, the remaining forces of CORE and Carminia are retreating. The price we paid was high, but the battle for Mora Secundis is finally over.</Data></Cell><Cell><Data ss:Type="String">Udało nam się! Pozbawione przywódców resztki sił ŚWIAT-a i Carminii wycofują się. Zapłaciliśmy wysoką cenę, ale bitwa o Mora Secundis wreszcie się zakończyła.</Data></Cell><Cell ss:Index="7"><Data ss:Type="String">Story Piece. Speaker: player character (any gender)</Data></Cell></Row><Row ss:AutoFitHeight="0"><Cell><Data ss:Type="String">MEET_CLAUDIUS_PROTON_HOSTILE_MESSAGE</Data></Cell><Cell><Data ss:Type="String">DESCRIPTION</Data></Cell><Cell><Data ss:Type="String">Every experiment can have undesired side effects. To reach perfection, some unpleasantries are unavoidable. One only has to make sure to dispose of specimens that are no longer required.[br/][br/]Acting against CORE is inanity. Reassembly will cure you of this ignorance.</Data></Cell><Cell><Data ss:Type="String">Każdy eksperyment może mieć niepożądane skutki uboczne. W drodze ku doskonałości trzeba się liczyć z pewnymi niedogodnościami, jakich nie sposób uniknąć. Należy jedynie zadbać o to, żeby niepotrzebne osobniki zostały zutylizowane.[br/][br/]Działanie przeciwko ŚWIAT-owi pozbawione jest sensu. Przebudowa wyleczy cię z tej ignorancji.</Data></Cell><Cell ss:Index="7"><Data ss:Type="String">Story Piece. Speaker: Claudius Proton (Assembly Male)</Data></Cell></Row><Row ss:AutoFitHeight="0"><Cell><Data ss:Type="String">MEET_TIK_JI_GLUX_HOSTILE_MESSAGE</Data></Cell><Cell><Data ss:Type="String">DESCRIPTION</Data></Cell><Cell><Data ss:Type="String">Krz’Chto’Rha! CORE brought the fire to the Kir’Ko Te’Naq, so that they could punish anyone causing sorrow to the swarm.[br/][br/]Burn, {STR_LeaderName}! Burn like a firefly caught in a blistering wildfire!</Data></Cell><Cell><Data ss:Type="String">Krz’Chto’Rha! ŚWIAT dał Kir’Ko Te’Naq ogień, by mogli ukarać każdego, kto przynosi ból rojowi.[br/][br/]Płoń, {STR_LeaderName}! Płoń niczym świetlik w straszliwym pożarze lasu!</Data></Cell><Cell ss:Index="7"><Data ss:Type="String">Story Piece. Speaker: Tik Ji'Glux (Kir'Ko female). Kir'Ko Te'Naq is a Kir'Ko clan</Data></Cell></Row><Row ss:AutoFitHeight="0"><Cell><Data ss:Type="String">MEET_YURIY_FRANKOV_HOSTILE_MESSAGE</Data></Cell><Cell><Data ss:Type="String">DESCRIPTION</Data></Cell><Cell><Data ss:Type="String">The Celestian light is the hammer, CORE the anvil. We all are the metal that is tempered into the different gears forming their clockwork of perfection.[br/][br/]Your alloy has been infused with impurity, {STR_LeaderName}. It must be melted down in the radiant heat of the enlightened.</Data></Cell><Cell><Data ss:Type="String">Światło Niebian jest młotem, a ŚWIAT – kowadłem. Wszyscy jesteśmy metalem, z którego formowane są różne tryby tworzące razem mechanizm doskonałości.[br/][br/]{STR_LeaderName}, twój stop jest zanieczyszczony. Musi zostać przekształcony w jaśniejącym ogniu oświeconych.</Data></Cell><Cell ss:Index="7"><Data ss:Type="String">Story Piece. Speaker: Yuriy Frankov (DVAR male). Celestian is a in-game secret tech</Data></Cell></Row><Row ss:AutoFitHeight="0"><Cell><Data ss:Type="String">MEET_EVA_MONTINGA_HOSTILE_MESSAGE</Data></Cell><Cell><Data ss:Type="String">DESCRIPTION</Data></Cell><Cell><Data ss:Type="String">Biological organisms are fascinating entities. Some are resourceful, others tenacious and treacherous. Yet others astound us with their abundance of color and beauty. The Alpha Strain collects and connects them all. When you fall, {STR_LeaderName}, you may find comfort in the fact that your DNA will persist within the Xenoplague compendium.</Data></Cell><Cell><Data ss:Type="String">Organizmy oparte na węglu to fascynujące istoty. Niektóre są zaradne, inne nieustępliwe i zdradzieckie, a jeszcze inne zachwycają swym pięknem i bogactwem kolorów. Szczep Alfa zbiera i łączy je wszystkie. {STR_LeaderName}, jeżeli zawiedziesz, niech pocieszy cię świadomość, że twoje DNA przetrwa w kompendium Ksenozarazy.</Data></Cell><Cell ss:Index="7"><Data ss:Type="String">Story Piece. Speaker: Eva Montinga (Vanguard Female). Xenoplague is a secret tech. Alpha Strain is a form of Xenoplague infection</Data></Cell></Row><Row ss:AutoFitHeight="0"><Cell><Data ss:Type="String">MEET_GIVORI_ARDELLI_HOSTILE_MESSAGE</Data></Cell><Cell><Data ss:Type="String">DESCRIPTION</Data></Cell><Cell><Data ss:Type="String">From the darkness they come. Beyond the veil they lurk. Their harmony requires sacrifice. Empress Carminia is their herald. You have chosen the path of pain, {STR_LeaderName}. Breaking you will be a delightful exercise.</Data></Cell><Cell><Data ss:Type="String">Przybywają z ciemności. Ukrywają się za zasłoną. Ich harmonia wymaga poświęcenia. Cesarzowa Carminia jest ich heroldem. {STR_LeaderName}, kroczysz ścieżką bólu. Złamanie cię będzie rozkosznym wyzwaniem.</Data></Cell><Cell ss:Index="7"><Data ss:Type="String">Story Piece. Speaker: Givori Ardelli (Syndicate male). </Data></Cell></Row><Row ss:AutoFitHeight="0"><Cell><Data ss:Type="String">MEET_ZARAI_LOREG_HOSTILE_MESSAGE</Data></Cell><Cell><Data ss:Type="String">DESCRIPTION</Data></Cell><Cell><Data ss:Type="String">Life is virtual. It is the sum of your perceptions and emotions. Uploading your consciousness is merely changing the rules of how you process the world’s input.[br/][br/]Your cerebral matrix requires an update, {STR_LeaderName}. Empress Carminia is leading our technological revolution. You cannot stop us.</Data></Cell><Cell><Data ss:Type="String">Życie jest pozorne. To suma twoich doznań i emocji. Wgranie swojej świadomości jest jedynie zmianą zasady przetwarzania płynących ze świata bodźców.[br/][br/]{STR_LeaderName}, twoja macierz mózgowa wymaga aktualizacji. Cesarzowa Carminia stoi na czele naszej technologicznej rewolucji. Nie możesz nas powstrzymać.</Data></Cell><Cell ss:Index="7"><Data ss:Type="String">Story Piece. Speaker: Zarai Loreg (Amazon Female).</Data></Cell></Row><Row ss:AutoFitHeight="0"><Cell><Data ss:Type="String">PARAGON_PROLONG_WAR_MESSAGE</Data></Cell><Cell><Data ss:Type="String">DESCRIPTION</Data></Cell><Cell><Data ss:Type="String">We accept the tribute you have paid to the Paragon. However, be aware that hostilities between our people cannot cease while you are opposing the will of the empress. Know that the resources you sent us will serve to restore the Star Union to its former glory.</Data></Cell><Cell><Data ss:Type="String">Wcielenie przyjmuje twój hołd. Zważ jednakże, iż wrogość między naszymi nacjami nie ustanie, dopóki sprzeciwiasz się woli cesarzowej. Wiedz, że wysłane przez ciebie zasoby zostaną wykorzystane w dziele przywrócenia Związkowi Gwiezdnemu jego dawnej chwały.</Data></Cell><Cell ss:Index="7"><Data ss:Type="String">Story Piece. Speaker: Paragon unit (male)</Data></Cell></Row><Row ss:AutoFitHeight="0"><Cell><Data ss:Type="String">AUTONOM_PROLONG_WAR_MESSAGE</Data></Cell><Cell><Data ss:Type="String">DESCRIPTION</Data></Cell><Cell><Data ss:Type="String">Appeasement protocol override in progress. Diplomatic status update denied. Cause: Target subject opposed CORE. Hostile interaction prolonged. All rebel activity must be terminated.</Data></Cell><Cell><Data ss:Type="String">Nadpisywanie protokołu łagodzącego. Aktualizacja relacji dyplomatycznych: odrzucono. Przyczyna: cel sprzeciwił się ŚWIAT-owi. Przedłużono wrogie stosunki. Należy usunąć wszystkich buntowników.</Data></Cell><Cell ss:Index="7"><Data ss:Type="String">Story Piece. Speaker: Autonom unit (robot)</Data></Cell></Row><Row ss:AutoFitHeight="0"><Cell><Data ss:Type="String">RELATION_MODIFIER_CORE_ALLIED</Data></Cell><Cell><Data ss:Type="String">DESCRIPTION</Data></Cell><Cell><Data ss:Type="String">Joined forces with CORE</Data></Cell><Cell><Data ss:Type="String">Połączono siły ze ŚWIAT-em.</Data></Cell><Cell ss:Index="7"><Data ss:Type="String">Relation Modifier</Data></Cell></Row><Row ss:AutoFitHeight="0"><Cell><Data ss:Type="String">RELATION_MODIFIER_CORE_OPPOSED</Data></Cell><Cell><Data ss:Type="String">DESCRIPTION</Data></Cell><Cell><Data ss:Type="String">Opposed CORE</Data></Cell><Cell><Data ss:Type="String">Sprzeciwiono się ŚWIAT-owi.</Data></Cell><Cell ss:Index="7"><Data ss:Type="String">Relation Modifier</Data></Cell></Row><Row ss:AutoFitHeight="0"><Cell><Data ss:Type="String">CASUS_BELLI_CORE_OPPOSED</Data></Cell><Cell><Data ss:Type="String">DESCRIPTION</Data></Cell><Cell><Data ss:Type="String">Betrayed CORE</Data></Cell><Cell><Data ss:Type="String">Zdradzono ŚWIAT.</Data></Cell><Cell ss:Index="7"><Data ss:Type="String">Casus Belli Description</Data></Cell></Row><Row ss:AutoFitHeight="0"><Cell><Data ss:Type="String">RELATION_MODIFIER_EMPRESS_ALLIED</Data></Cell><Cell><Data ss:Type="String">DESCRIPTION</Data></Cell><Cell><Data ss:Type="String">Joined forces with Empress Carminia</Data></Cell><Cell><Data ss:Type="String">Połączono siły z cesarzową Carminią.</Data></Cell><Cell ss:Index="7"><Data ss:Type="String">Relation Modifier</Data></Cell></Row><Row ss:AutoFitHeight="0"><Cell><Data ss:Type="String">RELATION_MODIFIER_EMPRESS_OPPOSED</Data></Cell><Cell><Data ss:Type="String">DESCRIPTION</Data></Cell><Cell><Data ss:Type="String">Opposed Empress Carminia</Data></Cell><Cell><Data ss:Type="String">Sprzeciwiono się cesarzowej Carminii.</Data></Cell><Cell ss:Index="7"><Data ss:Type="String">Relation Modifier</Data></Cell></Row><Row ss:AutoFitHeight="0"><Cell><Data ss:Type="String">CASUS_BELLI_EMPRESS_OPPOSED</Data></Cell><Cell><Data ss:Type="String">DESCRIPTION</Data></Cell><Cell><Data ss:Type="String">Betrayed Empress Carminia</Data></Cell><Cell><Data ss:Type="String">Zdradzono cesarzową Carminię.</Data></Cell><Cell ss:Index="7"><Data ss:Type="String">Casus Belli Description</Data></Cell></Row><Row ss:AutoFitHeight="0"><Cell><Data ss:Type="String">RELATION_MODIFIER_INDIE_ALLIED</Data></Cell><Cell><Data ss:Type="String">DESCRIPTION</Data></Cell><Cell><Data ss:Type="String">United against CORE and Empress Carminia</Data></Cell><Cell><Data ss:Type="String">Zjednoczono siły przeciwko ŚWIAT-owi i cesarzowej Carminii.</Data></Cell><Cell ss:Index="7"><Data ss:Type="String">Relation Modifier</Data></Cell></Row><Row ss:AutoFitHeight="0"><Cell><Data ss:Type="String">RELATION_MODIFIER_INDIE_ENEMIES</Data></Cell><Cell><Data ss:Type="String">DESCRIPTION</Data></Cell><Cell><Data ss:Type="String">Working for the autocratic forces of the past</Data></Cell><Cell><Data ss:Type="String">Współpraca z dawnymi despotycznymi reżimami.</Data></Cell><Cell ss:Index="7"><Data ss:Type="String">Relation Modifier</Data></Cell></Row><Row ss:AutoFitHeight="0"><Cell><Data ss:Type="String">CASUS_BELLI_OLD_POWERS</Data></Cell><Cell><Data ss:Type="String">DESCRIPTION</Data></Cell><Cell><Data ss:Type="String">Opposes a liberal Star Union</Data></Cell><Cell><Data ss:Type="String">Sprzeciwienie się liberalnemu Związkowi Gwiezdnemu.</Data></Cell><Cell ss:Index="7"><Data ss:Type="String">Casus Belli Description</Data></Cell></Row><Row ss:AutoFitHeight="0"><Cell><Data ss:Type="String">CORE_ALLIANCE_MESSAGE_PAGE_08_B_SHAE_MARA</Data></Cell><Cell><Data ss:Type="String">DESCRIPTION</Data></Cell><Cell><Data ss:Type="String">As an impartial machine, CORE doesn’t share the laughable sentiments of empathy that limited the free Syndicate market. With CORE reinstated our old conflict with the Star Union can surely be resolved in a manner that is beneficial to everyone...</Data></Cell><Cell><Data ss:Type="String">ŚWIAT – jako bezstronna maszyna – nie podziela śmiechu wartych sentymentów, które ograniczały wolny rynek Syndykatu. Po przywróceniu władzy ŚWIAT-a nasz stary konflikt ze Związkiem Gwiezdnym z pewnością da się rozstrzygnąć w sposób korzystny dla wszystkich...</Data></Cell><Cell ss:Index="7"><Data ss:Type="String">Story Piece. Speaker: Syndicate commander (any gender, female by default)</Data></Cell></Row><Row><Cell><Data ss:Type="String"/></Cell><Cell><Data ss:Type="String"/></Cell><Cell><Data ss:Type="String"/></Cell><Cell ss:Index="7"><Data ss:Type="String">We were travelling the Nexus Network towards Union Prime when we got pulled in by one of the Void Torrents. Our ship was launched down the funnel until we were spilled out by what can only be described as a super-sized Spatial Rift, lingering like a menacing cloud that could at any moment turn into a violent storm.</Data></Cell><Cell><Data ss:Type="String">Arrival scene intro text. Added for context. Speaker: Player Character (any possible)</Data></Cell></Row><Row><Cell><Data ss:Type="String"/></Cell><Cell><Data ss:Type="String"/></Cell><Cell><Data ss:Type="String"/></Cell><Cell ss:Index="7"><Data ss:Type="String">We’ve got company. In the few minutes since our arrival the rift already spilled out dozens of damaged or destroyed vessels, slowly turning this area into a scrapyard. I recognize ship designs from all across the Union, though some debris seems completely alien. By the looks of it this rift may not only be the new central hub of the Nexus Network, but of the funnels and torrents within the Void itself.</Data></Cell><Cell><Data ss:Type="String">Arrival scene intro text. Added for context. Speaker: Player Character (any possible)</Data></Cell></Row><Row><Cell><Data ss:Type="String"/></Cell><Cell><Data ss:Type="String"/></Cell><Cell><Data ss:Type="String"/></Cell><Cell ss:Index="7"><Data ss:Type="String">Some of the stranded ships have started moving towards Mora Secundis, the capital world of this region. Once a thriving, metropolitan planet, Mora Secundis appears to be shredded in space, only parts of it still clutching at the strings of this reality. Deadly or not, its position next to the super-rift now makes it the most important target within the entire Union.</Data></Cell><Cell><Data ss:Type="String">Arrival scene intro text. Added for context. Speaker: Player Character (any possible). Mora Secundis is the name of the world</Data></Cell></Row><Row><Cell><Data ss:Type="String"/></Cell><Cell><Data ss:Type="String"/></Cell><Cell><Data ss:Type="String"/></Cell><Cell ss:Index="7"><Data ss:Type="String">The race is on and we are only one in a dozen. I don’t know which battles lie ahead or what enemies we are about to face, but I feel that for the better or the worse the future of the Star Union will be decided here on Mora Secundis.</Data></Cell><Cell><Data ss:Type="String">Arrival scene intro text. Added for context. Speaker: Player Character (any possible)</Data></Cell></Row></Table><WorksheetOptions xmlns="urn:schemas-microsoft-com:office:excel"><Unsynced/><Print><ValidPrinterInfo/><HorizontalResolution>600</HorizontalResolution><VerticalResolution>600</VerticalResolution></Print><Selected/><Panes><Pane><Number>3</Number><ActiveRow>36</ActiveRow><ActiveCol>2</ActiveCol></Pane></Panes><ProtectObjects>False</ProtectObjects><ProtectScenarios>False</ProtectScenarios></WorksheetOptions></Worksheet></Workbook>